zebra/__init__.py
zebra/__main__.py
zebra/cli.py
zebra/decorators.py
zebra/docker_client.py
zebra/docker_executable.py
zebra/exceptions.py
zebra/locale/zebra.en.yml
zebra/pipeline_model.py
zebra/subprocess.py
acidcli_zebra-4.14.0.dist-info/METADATA
acidcli_zebra-4.14.0.dist-info/WHEEL
acidcli_zebra-4.14.0.dist-info/entry_points.txt
acidcli_zebra-4.14.0.dist-info/RECORD
