Metadata-Version: 2.1
Name: acidcli-zebra
Version: 4.14.0
Summary: Run Gitlab pipelines locally
License: MIT
Author: ACIDSpace
Author-email: support@acidspace.nl
Requires-Python: >=3.8,<4.0
Classifier: Development Status :: 3 - Alpha
Classifier: Intended Audience :: Developers
Classifier: License :: OSI Approved :: MIT License
Classifier: Programming Language :: Python :: 3
Classifier: Programming Language :: Python :: 3.8
Classifier: Programming Language :: Python :: 3.9
Classifier: Programming Language :: Python :: 3.10
Classifier: Programming Language :: Python :: 3.11
Classifier: Programming Language :: Python :: 3
Requires-Dist: docker (>=6.0.1,<7.0.0)
Requires-Dist: loguru (>=0.6.0,<0.7.0)
Requires-Dist: pyfiglet (>=0.8.post1,<0.9)
Requires-Dist: python-dotenv (>=0.21.0,<0.22.0)
Requires-Dist: python-i18n[yaml] (>=0.3.9,<0.4.0)
Requires-Dist: pyyaml (>=6.0.1,<7.0.0)
Project-URL: issues, https://jira.acidspace.nl
